{
  "subject": "boxscore",
  "copyright": "Copyright 2017 MLB Advanced Media, L.P.  Use of any content on this page acknowledges agreement to the terms posted here http://gdx.mlb.com/components/copyright.txt",
  "data": {
    "boxscore": {
      "home_sname": "Cleveland",
      "away_fname": "New York Yankees",
      "game_info": "\n      <game_score>Nova 44; Bauer 37.<\/game_score><br/>\n      <wild_pitches>Nova.<\/wild_pitches><br/>\n      <pitches_to_strikes>Nova 82-52; Betances 22-16; Miller, A 12-9; Chapman 28-21; Bauer 89-59; House 8-5; Otero 9-8; Shaw, B 18-10; Allen 19-12.<\/pitches_to_strikes><br/>\n      <groundouts_to_flyouts>Nova 9-1; Betances 3-0; Miller, A 1-0; Chapman 1-0; Bauer 5-3; House 0-0; Otero 1-0; Shaw, B 2-0; Allen 0-0.<\/groundouts_to_flyouts><br/>\n      <batters_faced>Nova 21; Betances 6; Miller, A 3; Chapman 5; Bauer 27; House 1; Otero 3; Shaw, B 5; Allen 5.<\/batters_faced><br/>\n      <inherited_runners_scored>Betances 1-1; House 1-1.<\/inherited_runners_scored><br/>\n      <umpires>\n         <umpire id=\"483564\" position=\"HP\" name=\"Dan Bellino\"><\/umpire>\n         <umpire id=\"427206\" position=\"1B\" name=\"Tom Hallion\"><\/umpire>\n         <umpire id=\"427093\" position=\"2B\" name=\"Phil Cuzzi\"><\/umpire>\n         <umpire id=\"594151\" position=\"3B\" name=\"Ramon De Jesus\"><\/umpire>\n      <\/umpires>\n      <weather>83 degrees, clear<\/weather>\n      <wind>3 mph, L to R<\/wind>\n      <weather>7:10 PM<\/weather>\n      <time>3:00<\/time>\n      <attendance>23,848<\/attendance>\n      <wind>Progressive Field<\/wind>\n      <wind>July 7, 2016<\/wind>",
      "home_loss": "34",
      "venue_name": "Progressive Field",
      "linescore": {
        "home_team_runs": "4",
        "home_team_errors": "0",
        "home_team_hits": "7",
        "inning_line_score": [
          {
            "home": "0",
            "away": "0",
            "inning": "1"
          },
          {
            "home": "0",
            "away": "0",
            "inning": "2"
          },
          {
            "home": "2",
            "away": "0",
            "inning": "3"
          },
          {
            "home": "0",
            "away": "0",
            "inning": "4"
          },
          {
            "home": "0",
            "away": "2",
            "inning": "5"
          },
          {
            "home": "2",
            "away": "3",
            "inning": "6"
          },
          {
            "home": "0",
            "away": "0",
            "inning": "7"
          },
          {
            "home": "0",
            "away": "0",
            "inning": "8"
          },
          {
            "home": "0",
            "away": "0",
            "inning": "9"
          }
        ],
        "away_team_errors": "0",
        "away_team_runs": "5",
        "away_team_hits": "11"
      },
      "home_sport_code": "mlb",
      "away_wins": "42",
      "game_pk": "448150",
      "status_ind": "F",
      "date": "July 7, 2016",
      "pitching": [
        {
          "hr": "2",
          "so": "10",
          "r": "4",
          "pitcher": [
            {
              "hr": "2",
              "s_er": "46",
              "np": "82",
              "name_display_first_last": "Ivan Nova",
              "s_h": "91",
              "era": "5.18",
              "game_score": "44",
              "bs": "0",
              "pos": "P",
              "id": "467100",
              "name": "Nova",
              "bf": "21",
              "sv": "1",
              "bb": "0",
              "note": "(W, 6-5)",
              "hld": "0",
              "so": "6",
              "s_so": "61",
              "l": "5",
              "win": "true",
              "h": "5",
              "s_ip": "80.0",
              "w": "6",
              "s_bb": "17",
              "s_r": "47",
              "s": "52",
              "r": "4",
              "er": "4",
              "out": "16"
            },
            {
              "hr": "0",
              "s_er": "12",
              "np": "22",
              "name_display_first_last": "Dellin Betances",
              "s_h": "32",
              "era": "2.53",
              "game_score": "50",
              "bs": "2",
              "pos": "P",
              "id": "476454",
              "name": "Betances",
              "bf": "6",
              "sv": "0",
              "bb": "0",
              "note": "(H, 21)",
              "hld": "21",
              "so": "2",
              "s_so": "76",
              "l": "4",
              "h": "1",
              "s_ip": "42.2",
              "w": "2",
              "s_bb": "9",
              "s_r": "15",
              "s": "16",
              "r": "0",
              "er": "0",
              "out": "5"
            },
            {
              "hr": "0",
              "s_er": "6",
              "np": "12",
              "name_display_first_last": "Andrew Miller",
              "s_h": "20",
              "era": "1.43",
              "game_score": "47",
              "bs": "1",
              "pos": "P",
              "id": "453192",
              "name": "Miller, A",
              "bf": "3",
              "sv": "7",
              "bb": "0",
              "note": "(H, 14)",
              "hld": "14",
              "so": "1",
              "s_so": "67",
              "l": "1",
              "h": "0",
              "s_ip": "37.2",
              "w": "5",
              "s_bb": "5",
              "s_r": "7",
              "s": "9",
              "r": "0",
              "er": "0",
              "out": "3"
            },
            {
              "hr": "0",
              "s_er": "7",
              "save": "true",
              "np": "28",
              "name_display_first_last": "Aroldis Chapman",
              "s_h": "18",
              "era": "2.74",
              "game_score": "43",
              "bs": "1",
              "pos": "P",
              "id": "547973",
              "name": "Chapman",
              "bf": "5",
              "sv": "17",
              "bb": "1",
              "note": "(S, 17)",
              "hld": "0",
              "so": "1",
              "s_so": "34",
              "l": "0",
              "h": "1",
              "s_ip": "23.0",
              "w": "2",
              "s_bb": "5",
              "s_r": "8",
              "s": "21",
              "r": "0",
              "er": "0",
              "out": "3"
            }
          ],
          "bf": "35",
          "era": "4.38",
          "team_flag": "away",
          "bb": "1",
          "er": "4",
          "h": "7",
          "out": "27"
        },
        {
          "hr": "1",
          "so": "9",
          "r": "5",
          "pitcher": [
            {
              "hr": "1",
              "s_er": "37",
              "loss": "true",
              "np": "89",
              "name_display_first_last": "Trevor Bauer",
              "s_h": "86",
              "era": "3.30",
              "game_score": "37",
              "bs": "0",
              "pos": "P",
              "id": "545333",
              "name": "Bauer",
              "bf": "27",
              "sv": "0",
              "bb": "2",
              "note": "(L, 7-3)",
              "hld": "0",
              "so": "4",
              "s_so": "91",
              "l": "3",
              "h": "8",
              "s_ip": "101.0",
              "w": "7",
              "s_bb": "35",
              "s_r": "38",
              "s": "59",
              "r": "5",
              "er": "5",
              "out": "17"
            },
            {
              "hr": "0",
              "s_er": "0",
              "np": "8",
              "name_display_first_last": "TJ House",
              "s_h": "2",
              "era": "0.00",
              "game_score": "40",
              "bs": "0",
              "pos": "P",
              "id": "543334",
              "name": "House",
              "bf": "1",
              "sv": "0",
              "bb": "0",
              "hld": "0",
              "so": "0",
              "s_so": "2",
              "l": "0",
              "h": "1",
              "s_ip": "2.0",
              "w": "0",
              "s_bb": "0",
              "s_r": "0",
              "s": "5",
              "r": "0",
              "er": "0",
              "out": "1"
            },
            {
              "hr": "0",
              "s_er": "5",
              "np": "9",
              "name_display_first_last": "Dan Otero",
              "s_h": "29",
              "era": "1.32",
              "game_score": "48",
              "bs": "0",
              "pos": "P",
              "id": "519096",
              "name": "Otero",
              "bf": "3",
              "sv": "1",
              "bb": "0",
              "hld": "0",
              "so": "2",
              "s_so": "33",
              "l": "1",
              "h": "0",
              "s_ip": "34.0",
              "w": "2",
              "s_bb": "7",
              "s_r": "6",
              "s": "8",
              "r": "0",
              "er": "0",
              "out": "3"
            },
            {
              "hr": "0",
              "s_er": "16",
              "np": "18",
              "name_display_first_last": "Bryan Shaw",
              "s_h": "32",
              "era": "4.28",
              "game_score": "43",
              "bs": "2",
              "pos": "P",
              "id": "543766",
              "name": "Shaw, B",
              "bf": "5",
              "sv": "0",
              "bb": "2",
              "hld": "14",
              "so": "1",
              "s_so": "36",
              "l": "3",
              "h": "0",
              "s_ip": "33.2",
              "w": "1",
              "s_bb": "15",
              "s_r": "16",
              "s": "10",
              "r": "0",
              "er": "0",
              "out": "3"
            },
            {
              "hr": "0",
              "s_er": "12",
              "np": "19",
              "name_display_first_last": "Cody Allen",
              "s_h": "25",
              "era": "2.95",
              "game_score": "44",
              "bs": "2",
              "pos": "P",
              "id": "592102",
              "name": "Allen",
              "bf": "5",
              "sv": "18",
              "bb": "0",
              "hld": "0",
              "so": "2",
              "s_so": "45",
              "l": "3",
              "h": "2",
              "s_ip": "36.2",
              "w": "2",
              "s_bb": "18",
              "s_r": "14",
              "s": "12",
              "r": "0",
              "er": "0",
              "out": "3"
            }
          ],
          "bf": "41",
          "era": "3.63",
          "team_flag": "home",
          "bb": "4",
          "er": "5",
          "h": "11",
          "out": "27"
        }
      ],
      "home_id": "114",
      "away_loss": "43",
      "game_info_es": "\n      <game_score>Nova 44; Bauer 37.<\/game_score><br/>\n      <wild_pitches>Nova.<\/wild_pitches><br/>\n      <pitches_to_strikes>Nova 82-52; Betances 22-16; Miller, A 12-9; Chapman 28-21; Bauer 89-59; House 8-5; Otero 9-8; Shaw, B 18-10; Allen 19-12.<\/pitches_to_strikes><br/>\n      <groundouts_to_flyouts>Nova 9-1; Betances 3-0; Miller, A 1-0; Chapman 1-0; Bauer 5-3; House 0-0; Otero 1-0; Shaw, B 2-0; Allen 0-0.<\/groundouts_to_flyouts><br/>\n      <batters_faced>Nova 21; Betances 6; Miller, A 3; Chapman 5; Bauer 27; House 1; Otero 3; Shaw, B 5; Allen 5.<\/batters_faced><br/>\n      <inherited_runners_scored>Betances 1-1; House 1-1.<\/inherited_runners_scored><br/>\n      <umpires>\n         <umpire id=\"483564\" position=\"HP\" name=\"Dan Bellino\"><\/umpire>\n         <umpire id=\"427206\" position=\"1B\" name=\"Tom Hallion\"><\/umpire>\n         <umpire id=\"427093\" position=\"2B\" name=\"Phil Cuzzi\"><\/umpire>\n         <umpire id=\"594151\" position=\"3B\" name=\"Ramon De Jesus\"><\/umpire>\n      <\/umpires>\n      <weather>83 degrees, clear<\/weather>\n      <wind>3 mph, L to R<\/wind>\n      <weather>7:10 PM<\/weather>\n      <time>3:00<\/time>\n      <attendance>23,848<\/attendance>\n      <wind>Progressive Field<\/wind>\n      <wind>July 7, 2016<\/wind>",
      "batting": [
        {
          "hr": "2",
          "d": "2",
          "da": "10",
          "so": "10",
          "batter": [
            {
              "hr": "0",
              "sac": "0",
              "name_display_first_last": "Carlos Santana",
              "s_h": "78",
              "s_hr": "19",
              "s_rbi": "46",
              "pos": "DH",
              "id": "467793",
              "rbi": "0",
              "bo": "100",
              "lob": "0",
              "name": "Santana, C",
              "slg": ".487",
              "avg": ".248",
              "bb": "0",
              "fldg": ".000",
              "ops": ".838",
              "hbp": "0",
              "d": "1",
              "e": "0",
              "so": "1",
              "a": "0",
              "s_so": "49",
              "sf": "0",
              "h": "1",
              "cs": "0",
              "obp": ".351",
              "s_bb": "50",
              "s_r": "50",
              "t": "0",
              "ao": "0",
              "r": "1",
              "sb": "0",
              "po": "0",
              "ab": "4",
              "go": "2"
            },
            {
              "hr": "1",
              "sac": "0",
              "name_display_first_last": "Jason Kipnis",
              "s_h": "88",
              "s_hr": "12",
              "s_rbi": "47",
              "pos": "2B",
              "id": "543401",
              "rbi": "1",
              "bo": "200",
              "lob": "0",
              "name": "Kipnis",
              "slg": ".453",
              "avg": ".267",
              "bb": "0",
              "fldg": "1.000",
              "ops": ".779",
              "hbp": "0",
              "d": "1",
              "e": "0",
              "so": "1",
              "a": "5",
              "s_so": "77",
              "sf": "0",
              "h": "2",
              "cs": "0",
              "obp": ".326",
              "s_bb": "28",
              "s_r": "45",
              "t": "0",
              "ao": "0",
              "r": "2",
              "sb": "0",
              "po": "2",
              "ab": "4",
              "go": "1"
            },
            {
              "hr": "0",
              "sac": "0",
              "name_display_first_last": "Francisco Lindor",
              "s_h": "97",
              "s_hr": "10",
              "s_rbi": "43",
              "pos": "SS",
              "id": "596019",
              "rbi": "0",
              "bo": "300",
              "lob": "1",
              "name": "Lindor",
              "slg": ".449",
              "avg": ".298",
              "bb": "0",
              "fldg": "1.000",
              "ops": ".802",
              "hbp": "0",
              "d": "0",
              "e": "0",
              "so": "0",
              "a": "2",
              "s_so": "48",
              "sf": "0",
              "h": "1",
              "cs": "0",
              "obp": ".353",
              "s_bb": "30",
              "s_r": "54",
              "t": "0",
              "ao": "1",
              "r": "0",
              "sb": "0",
              "po": "3",
              "ab": "4",
              "go": "2"
            },
            {
              "hr": "0",
              "sac": "0",
              "name_display_first_last": "Mike Napoli",
              "s_h": "72",
              "s_hr": "17",
              "s_rbi": "57",
              "pos": "1B",
              "id": "435063",
              "rbi": "1",
              "bo": "400",
              "lob": "1",
              "name": "Napoli",
              "slg": ".457",
              "avg": ".237",
              "bb": "1",
              "fldg": "1.000",
              "ops": ".769",
              "hbp": "0",
              "d": "0",
              "e": "0",
              "so": "1",
              "a": "1",
              "s_so": "116",
              "sf": "0",
              "h": "0",
              "cs": "0",
              "obp": ".312",
              "s_bb": "33",
              "s_r": "50",
              "t": "0",
              "ao": "0",
              "r": "0",
              "sb": "0",
              "po": "7",
              "ab": "3",
              "go": "2"
            },
            {
              "hr": "0",
              "sac": "0",
              "name_display_first_last": "Jose Ramirez",
              "s_h": "81",
              "s_hr": "4",
              "s_rbi": "34",
              "pos": "3B",
              "id": "608070",
              "rbi": "0",
              "bo": "500",
              "lob": "1",
              "name": "Ramirez, Js",
              "slg": ".423",
              "avg": ".296",
              "bb": "0",
              "fldg": ".000",
              "ops": ".778",
              "hbp": "0",
              "d": "0",
              "e": "0",
              "so": "1",
              "a": "0",
              "s_so": "33",
              "sf": "0",
              "h": "0",
              "cs": "0",
              "obp": ".355",
              "s_bb": "23",
              "s_r": "42",
              "t": "0",
              "ao": "0",
              "r": "0",
              "sb": "0",
              "po": "0",
              "ab": "4",
              "go": "3"
            },
            {
              "hr": "0",
              "sac": "0",
              "name_display_first_last": "Lonnie Chisenhall",
              "s_h": "61",
              "s_hr": "5",
              "s_rbi": "26",
              "pos": "RF",
              "id": "502082",
              "rbi": "0",
              "bo": "600",
              "lob": "0",
              "name": "Chisenhall",
              "slg": ".470",
              "avg": ".302",
              "bb": "0",
              "fldg": "1.000",
              "ops": ".820",
              "hbp": "0",
              "d": "0",
              "e": "0",
              "so": "1",
              "a": "0",
              "s_so": "37",
              "sf": "0",
              "h": "0",
              "cs": "0",
              "obp": ".350",
              "s_bb": "15",
              "s_r": "25",
              "t": "0",
              "ao": "0",
              "r": "0",
              "sb": "0",
              "po": "2",
              "ab": "3",
              "go": "2"
            },
            {
              "hr": "0",
              "sac": "0",
              "name_display_first_last": "Juan Uribe",
              "s_h": "45",
              "s_hr": "7",
              "s_rbi": "22",
              "pos": "PH",
              "id": "346874",
              "rbi": "0",
              "bo": "601",
              "lob": "0",
              "name": "Uribe",
              "slg": ".365",
              "avg": ".222",
              "bb": "0",
              "fldg": ".000",
              "note": "b-",
              "ops": ".643",
              "hbp": "0",
              "d": "0",
              "e": "0",
              "so": "0",
              "a": "0",
              "s_so": "41",
              "sf": "0",
              "h": "1",
              "cs": "0",
              "obp": ".278",
              "s_bb": "15",
              "s_r": "17",
              "t": "0",
              "ao": "0",
              "r": "0",
              "sb": "0",
              "po": "0",
              "ab": "1"
            },
            {
              "hr": "0",
              "sac": "0",
              "name_display_first_last": "Rajai Davis",
              "s_h": "72",
              "s_hr": "9",
              "s_rbi": "33",
              "pos": "LF",
              "id": "434658",
              "rbi": "0",
              "bo": "700",
              "lob": "2",
              "name": "Davis, R",
              "slg": ".444",
              "avg": ".271",
              "bb": "0",
              "fldg": "1.000",
              "ops": ".773",
              "hbp": "0",
              "d": "0",
              "e": "0",
              "so": "2",
              "a": "0",
              "s_so": "65",
              "sf": "0",
              "h": "0",
              "cs": "0",
              "obp": ".329",
              "s_bb": "21",
              "s_r": "44",
              "t": "0",
              "ao": "1",
              "r": "0",
              "sb": "0",
              "po": "4",
              "ab": "4",
              "go": "1"
            },
            {
              "hr": "1",
              "sac": "0",
              "name_display_first_last": "Tyler Naquin",
              "s_h": "49",
              "s_hr": "8",
              "s_rbi": "20",
              "pos": "CF",
              "id": "571980",
              "rbi": "1",
              "bo": "800",
              "lob": "2",
              "name": "Naquin",
              "slg": ".596",
              "avg": ".325",
              "bb": "0",
              "fldg": ".000",
              "ops": ".982",
              "hbp": "0",
              "d": "0",
              "e": "0",
              "so": "0",
              "a": "0",
              "s_so": "49",
              "sf": "0",
              "h": "2",
              "cs": "0",
              "obp": ".386",
              "s_bb": "14",
              "s_r": "25",
              "t": "0",
              "ao": "1",
              "r": "1",
              "sb": "1",
              "po": "0",
              "ab": "4",
              "go": "1"
            },
            {
              "hr": "0",
              "sac": "0",
              "name_display_first_last": "Chris Gimenez",
              "s_h": "15",
              "s_hr": "2",
              "s_rbi": "4",
              "pos": "C",
              "id": "460269",
              "rbi": "0",
              "bo": "900",
              "lob": "0",
              "name": "Gimenez",
              "slg": ".272",
              "avg": ".185",
              "bb": "0",
              "fldg": "1.000",
              "ops": ".502",
              "hbp": "0",
              "d": "0",
              "e": "0",
              "so": "2",
              "a": "0",
              "s_so": "22",
              "sf": "0",
              "h": "0",
              "cs": "0",
              "obp": ".230",
              "s_bb": "5",
              "s_r": "9",
              "t": "0",
              "ao": "0",
              "r": "0",
              "sb": "0",
              "po": "6",
              "ab": "2"
            },
            {
              "hr": "0",
              "sac": "0",
              "name_display_first_last": "Abraham Almonte",
              "s_h": "1",
              "s_hr": "0",
              "s_rbi": "0",
              "pos": "PH",
              "id": "501659",
              "rbi": "0",
              "bo": "901",
              "lob": "1",
              "name": "Almonte",
              "slg": ".222",
              "avg": ".111",
              "bb": "0",
              "fldg": ".000",
              "note": "a-",
              "ops": ".333",
              "hbp": "0",
              "d": "0",
              "e": "0",
              "so": "1",
              "a": "0",
              "s_so": "5",
              "sf": "0",
              "h": "0",
              "cs": "0",
              "obp": ".111",
              "s_bb": "0",
              "s_r": "0",
              "t": "0",
              "ao": "0",
              "r": "0",
              "sb": "0",
              "po": "0",
              "ab": "1"
            },
            {
              "hr": "0",
              "sac": "0",
              "name_display_first_last": "Yan Gomes",
              "s_h": "40",
              "s_hr": "8",
              "s_rbi": "31",
              "pos": "C",
              "id": "543228",
              "rbi": "0",
              "bo": "902",
              "lob": "0",
              "name": "Gomes",
              "slg": ".332",
              "avg": ".175",
              "bb": "0",
              "fldg": "1.000",
              "ops": ".539",
              "hbp": "0",
              "d": "0",
              "e": "0",
              "so": "0",
              "a": "0",
              "s_so": "63",
              "sf": "0",
              "h": "0",
              "cs": "0",
              "obp": ".207",
              "s_bb": "8",
              "s_r": "21",
              "t": "0",
              "ao": "0",
              "r": "0",
              "sb": "0",
              "po": "3",
              "ab": "0"
            },
            {
              "hr": "0",
              "sac": "0",
              "name_display_first_last": "Trevor Bauer",
              "s_h": "0",
              "s_hr": "0",
              "s_rbi": "0",
              "pos": "P",
              "id": "545333",
              "rbi": "0",
              "lob": "0",
              "name": "Bauer",
              "slg": ".000",
              "avg": ".000",
              "bb": "0",
              "fldg": ".000",
              "ops": ".000",
              "hbp": "0",
              "d": "0",
              "e": "0",
              "so": "0",
              "a": "0",
              "s_so": "3",
              "sf": "0",
              "h": "0",
              "cs": "0",
              "obp": ".000",
              "s_bb": "0",
              "s_r": "0",
              "t": "0",
              "ao": "0",
              "r": "0",
              "sb": "0",
              "po": "0",
              "ab": "0"
            },
            {
              "hr": "0",
              "sac": "0",
              "name_display_first_last": "TJ House",
              "s_h": "0",
              "s_hr": "0",
              "s_rbi": "0",
              "pos": "P",
              "id": "543334",
              "rbi": "0",
              "lob": "0",
              "name": "House",
              "slg": ".000",
              "avg": ".000",
              "bb": "0",
              "fldg": "1.000",
              "ops": ".000",
              "hbp": "0",
              "d": "0",
              "e": "0",
              "so": "0",
              "a": "1",
              "s_so": "0",
              "sf": "0",
              "h": "0",
              "cs": "0",
              "obp": ".000",
              "s_bb": "0",
              "s_r": "0",
              "t": "0",
              "ao": "0",
              "r": "0",
              "sb": "0",
              "po": "0",
              "ab": "0"
            },
            {
              "hr": "0",
              "sac": "0",
              "name_display_first_last": "Dan Otero",
              "s_h": "0",
              "s_hr": "0",
              "s_rbi": "0",
              "pos": "P",
              "id": "519096",
              "rbi": "0",
              "lob": "0",
              "name": "Otero",
              "slg": ".000",
              "avg": ".000",
              "bb": "0",
              "fldg": "1.000",
              "ops": ".000",
              "hbp": "0",
              "d": "0",
              "e": "0",
              "so": "0",
              "a": "1",
              "s_so": "0",
              "sf": "0",
              "h": "0",
              "cs": "0",
              "obp": ".000",
              "s_bb": "0",
              "s_r": "0",
              "t": "0",
              "ao": "0",
              "r": "0",
              "sb": "0",
              "po": "0",
              "ab": "0"
            },
            {
              "hr": "0",
              "sac": "0",
              "name_display_first_last": "Bryan Shaw",
              "s_h": "0",
              "s_hr": "0",
              "s_rbi": "0",
              "pos": "P",
              "id": "543766",
              "rbi": "0",
              "lob": "0",
              "name": "Shaw, B",
              "slg": ".000",
              "avg": ".000",
              "bb": "0",
              "fldg": ".000",
              "ops": ".000",
              "hbp": "0",
              "d": "0",
              "e": "0",
              "so": "0",
              "a": "0",
              "s_so": "0",
              "sf": "0",
              "h": "0",
              "cs": "0",
              "obp": ".000",
              "s_bb": "0",
              "s_r": "0",
              "t": "0",
              "ao": "0",
              "r": "0",
              "sb": "0",
              "po": "0",
              "ab": "0"
            },
            {
              "hr": "0",
              "sac": "0",
              "name_display_first_last": "Cody Allen",
              "s_h": "0",
              "s_hr": "0",
              "s_rbi": "0",
              "pos": "P",
              "id": "592102",
              "rbi": "0",
              "lob": "0",
              "name": "Allen",
              "slg": ".000",
              "avg": ".000",
              "bb": "0",
              "fldg": ".000",
              "ops": ".000",
              "hbp": "0",
              "d": "0",
              "e": "0",
              "so": "0",
              "a": "0",
              "s_so": "0",
              "sf": "0",
              "h": "0",
              "cs": "0",
              "obp": ".000",
              "s_bb": "0",
              "s_r": "0",
              "t": "0",
              "ao": "0",
              "r": "0",
              "sb": "0",
              "po": "0",
              "ab": "0"
            }
          ],
          "h": "7",
          "text_data_es": "\n         <doubles>Santana, C (16, Nova); Kipnis (17, Nova).<\/doubles><br/>\n         <home_runs>Naquin (8, 3rd entrada ante Nova, 0 en base, 0 out); Kipnis (12, 3rd entrada ante Nova, 0 en base, 2 out).<\/home_runs><br/>\n         <total_bases>Lindor; Santana, C 2; Kipnis 6; Uribe; Naquin 5.<\/total_bases><br/>\n         <rbi>Naquin (20); Kipnis (47); Napoli (57).<\/rbi><br/>\n         <two_out_rbi>Kipnis.<\/two_out_rbi><br/>\n         <risp_lob_two_out>Almonte; Naquin.<\/risp_lob_two_out><br/>\n         <team_risp>\n            \t\t\t\t\t\t\tde 1-6.\n         <\/team_risp>\n         <team_lob>4.<\/team_lob>\n         <stolen_bases>Naquin (3, 2nd base a Betances/McCann, B).<\/stolen_bases><br/>\n         <pickoffs>House (Ellsbury en 1st base).<\/pickoffs><br/><br/>",
          "note_es": "\n         <pinch_hitters>a-Bateó por Gimenez en la 7th. b-Bateó por Chisenhall en la 9th. <\/pinch_hitters>",
          "text_data": "\n         <doubles>Santana, C (16, Nova); Kipnis (17, Nova).<\/doubles><br/>\n         <home_runs>Naquin (8, 3rd inning off Nova, 0 on, 0 out); Kipnis (12, 3rd inning off Nova, 0 on, 2 out).<\/home_runs><br/>\n         <total_bases>Lindor; Santana, C 2; Kipnis 6; Uribe; Naquin 5.<\/total_bases><br/>\n         <rbi>Naquin (20); Kipnis (47); Napoli (57).<\/rbi><br/>\n         <two_out_rbi>Kipnis.<\/two_out_rbi><br/>\n         <risp_lob_two_out>Almonte; Naquin.<\/risp_lob_two_out><br/>\n         <team_risp>1-for-6.<\/team_risp>\n         <team_lob>4.<\/team_lob>\n         <stolen_bases>Naquin (3, 2nd base off Betances/McCann, B).<\/stolen_bases><br/>\n         <pickoffs>House (Ellsbury at 1st base).<\/pickoffs><br/><br/>",
          "obp": ".321",
          "rbi": "3",
          "lob": "8",
          "t": "0",
          "r": "4",
          "team_flag": "home",
          "ab": "34",
          "po": "27",
          "slg": ".433",
          "avg": ".259",
          "bb": "1",
          "note": "\n         <pinch_hitters>a-Struck out for Gimenez in the 7th. b-Singled for Chisenhall in the 9th. <\/pinch_hitters>",
          "ops": ".754"
        },
        {
          "hr": "1",
          "d": "0",
          "da": "14",
          "so": "9",
          "batter": [
            {
              "hr": "0",
              "sac": "0",
              "name_display_first_last": "Jacoby Ellsbury",
              "s_h": "79",
              "s_hr": "3",
              "s_rbi": "26",
              "pos": "CF",
              "id": "453056",
              "rbi": "1",
              "bo": "100",
              "lob": "3",
              "name": "Ellsbury",
              "slg": ".396",
              "avg": ".282",
              "bb": "0",
              "fldg": "1.000",
              "ops": ".744",
              "hbp": "0",
              "d": "0",
              "e": "0",
              "so": "0",
              "a": "0",
              "s_so": "39",
              "sf": "0",
              "h": "2",
              "cs": "1",
              "obp": ".348",
              "s_bb": "27",
              "s_r": "35",
              "t": "0",
              "ao": "2",
              "r": "0",
              "sb": "0",
              "po": "2",
              "ab": "5",
              "go": "1"
            },
            {
              "hr": "0",
              "sac": "0",
              "name_display_first_last": "Brett Gardner",
              "s_h": "73",
              "s_hr": "5",
              "s_rbi": "17",
              "pos": "LF",
              "id": "458731",
              "rbi": "1",
              "bo": "200",
              "lob": "1",
              "name": "Gardner",
              "slg": ".349",
              "avg": ".257",
              "bb": "0",
              "fldg": "1.000",
              "ops": ".703",
              "hbp": "0",
              "d": "0",
              "e": "0",
              "so": "3",
              "a": "0",
              "s_so": "58",
              "sf": "0",
              "h": "2",
              "cs": "0",
              "obp": ".354",
              "s_bb": "38",
              "s_r": "48",
              "t": "0",
              "ao": "0",
              "r": "0",
              "sb": "0",
              "po": "1",
              "ab": "5"
            },
            {
              "hr": "0",
              "sac": "0",
              "name_display_first_last": "Carlos Beltran",
              "s_h": "83",
              "s_hr": "19",
              "s_rbi": "54",
              "pos": "DH",
              "id": "136860",
              "rbi": "0",
              "bo": "300",
              "lob": "2",
              "name": "Beltran",
              "slg": ".555",
              "avg": ".293",
              "bb": "1",
              "fldg": ".000",
              "ops": ".889",
              "hbp": "0",
              "d": "0",
              "e": "0",
              "so": "1",
              "a": "0",
              "s_so": "57",
              "sf": "0",
              "h": "0",
              "cs": "0",
              "obp": ".334",
              "s_bb": "17",
              "s_r": "43",
              "t": "0",
              "ao": "2",
              "r": "0",
              "sb": "0",
              "po": "0",
              "ab": "4",
              "go": "1"
            },
            {
              "hr": "0",
              "sac": "0",
              "name_display_first_last": "Brian McCann",
              "s_h": "53",
              "s_hr": "13",
              "s_rbi": "35",
              "pos": "C",
              "id": "435263",
              "rbi": "0",
              "bo": "400",
              "lob": "4",
              "name": "McCann, B",
              "slg": ".434",
              "avg": ".232",
              "bb": "0",
              "fldg": "1.000",
              "ops": ".771",
              "hbp": "0",
              "d": "0",
              "e": "0",
              "so": "1",
              "a": "1",
              "s_so": "52",
              "sf": "0",
              "h": "1",
              "cs": "0",
              "obp": ".337",
              "s_bb": "32",
              "s_r": "34",
              "t": "0",
              "ao": "2",
              "r": "0",
              "sb": "0",
              "po": "9",
              "ab": "5",
              "go": "1"
            },
            {
              "hr": "0",
              "sac": "0",
              "name_display_first_last": "Mark Teixeira",
              "s_h": "40",
              "s_hr": "7",
              "s_rbi": "19",
              "pos": "1B",
              "id": "407893",
              "rbi": "0",
              "bo": "500",
              "lob": "3",
              "name": "Teixeira",
              "slg": ".318",
              "avg": ".190",
              "bb": "1",
              "fldg": "1.000",
              "ops": ".589",
              "hbp": "0",
              "d": "0",
              "e": "0",
              "so": "1",
              "a": "1",
              "s_so": "62",
              "sf": "0",
              "h": "0",
              "cs": "0",
              "obp": ".271",
              "s_bb": "23",
              "s_r": "21",
              "t": "0",
              "ao": "2",
              "r": "0",
              "sb": "0",
              "po": "14",
              "ab": "4",
              "go": "1"
            },
            {
              "hr": "0",
              "sac": "0",
              "name_display_first_last": "Starlin Castro",
              "s_h": "82",
              "s_hr": "10",
              "s_rbi": "31",
              "pos": "2B",
              "id": "516770",
              "rbi": "0",
              "bo": "600",
              "lob": "1",
              "name": "Castro, S",
              "slg": ".399",
              "avg": ".258",
              "bb": "0",
              "fldg": "1.000",
              "ops": ".694",
              "hbp": "0",
              "d": "0",
              "e": "0",
              "so": "2",
              "a": "4",
              "s_so": "58",
              "sf": "0",
              "h": "1",
              "cs": "0",
              "obp": ".295",
              "s_bb": "15",
              "s_r": "31",
              "t": "0",
              "ao": "0",
              "r": "1",
              "sb": "0",
              "po": "0",
              "ab": "4",
              "go": "1"
            },
            {
              "hr": "1",
              "sac": "0",
              "name_display_first_last": "Didi Gregorius",
              "s_h": "85",
              "s_hr": "10",
              "s_rbi": "39",
              "pos": "SS",
              "id": "544369",
              "rbi": "1",
              "bo": "700",
              "lob": "1",
              "name": "Gregorius",
              "slg": ".456",
              "avg": ".296",
              "bb": "0",
              "fldg": "1.000",
              "ops": ".779",
              "hbp": "0",
              "d": "0",
              "e": "0",
              "so": "0",
              "a": "4",
              "s_so": "33",
              "sf": "0",
              "h": "2",
              "cs": "0",
              "obp": ".323",
              "s_bb": "10",
              "s_r": "36",
              "t": "0",
              "ao": "0",
              "r": "2",
              "sb": "0",
              "po": "0",
              "ab": "4",
              "go": "2"
            },
            {
              "hr": "0",
              "sac": "0",
              "name_display_first_last": "Chase Headley",
              "s_h": "65",
              "s_hr": "7",
              "s_rbi": "26",
              "pos": "3B",
              "id": "452104",
              "rbi": "1",
              "bo": "800",
              "lob": "0",
              "name": "Headley",
              "slg": ".376",
              "avg": ".255",
              "bb": "1",
              "fldg": "1.000",
              "ops": ".708",
              "hbp": "0",
              "d": "0",
              "e": "0",
              "so": "1",
              "a": "4",
              "s_so": "64",
              "sf": "0",
              "h": "2",
              "cs": "0",
              "obp": ".332",
              "s_bb": "29",
              "s_r": "30",
              "t": "0",
              "ao": "0",
              "r": "2",
              "sb": "0",
              "po": "0",
              "ab": "3"
            },
            {
              "hr": "0",
              "sac": "0",
              "name_display_first_last": "Rob Refsnyder",
              "s_h": "22",
              "s_hr": "0",
              "s_rbi": "10",
              "pos": "RF",
              "id": "608701",
              "rbi": "1",
              "bo": "900",
              "lob": "0",
              "name": "Refsnyder",
              "slg": ".405",
              "avg": ".297",
              "bb": "1",
              "fldg": ".000",
              "ops": ".770",
              "hbp": "0",
              "d": "0",
              "e": "0",
              "so": "0",
              "a": "0",
              "s_so": "13",
              "sf": "1",
              "h": "1",
              "cs": "0",
              "obp": ".365",
              "s_bb": "9",
              "s_r": "12",
              "t": "0",
              "ao": "1",
              "r": "0",
              "sb": "0",
              "po": "0",
              "ab": "1"
            },
            {
              "hr": "0",
              "sac": "0",
              "name_display_first_last": "Aaron Hicks",
              "s_h": "36",
              "s_hr": "3",
              "s_rbi": "17",
              "pos": "RF",
              "id": "543305",
              "rbi": "0",
              "bo": "901",
              "lob": "2",
              "name": "Hicks",
              "slg": ".306",
              "avg": ".200",
              "bb": "0",
              "fldg": ".000",
              "ops": ".571",
              "hbp": "0",
              "d": "0",
              "e": "0",
              "so": "0",
              "a": "0",
              "s_so": "34",
              "sf": "0",
              "h": "0",
              "cs": "0",
              "obp": ".265",
              "s_bb": "17",
              "s_r": "18",
              "t": "0",
              "ao": "0",
              "r": "0",
              "sb": "0",
              "po": "0",
              "ab": "1",
              "go": "1"
            },
            {
              "hr": "0",
              "sac": "0",
              "name_display_first_last": "Ivan Nova",
              "s_h": "0",
              "s_hr": "0",
              "s_rbi": "0",
              "pos": "P",
              "id": "467100",
              "rbi": "0",
              "lob": "0",
              "name": "Nova",
              "slg": ".000",
              "avg": ".000",
              "bb": "0",
              "fldg": ".000",
              "ops": ".000",
              "hbp": "0",
              "d": "0",
              "e": "0",
              "so": "0",
              "a": "0",
              "s_so": "3",
              "sf": "0",
              "h": "0",
              "cs": "0",
              "obp": ".000",
              "s_bb": "0",
              "s_r": "0",
              "t": "0",
              "ao": "0",
              "r": "0",
              "sb": "0",
              "po": "0",
              "ab": "0"
            },
            {
              "hr": "0",
              "sac": "0",
              "name_display_first_last": "Dellin Betances",
              "s_h": "0",
              "s_hr": "0",
              "s_rbi": "0",
              "pos": "P",
              "id": "476454",
              "rbi": "0",
              "lob": "0",
              "name": "Betances",
              "slg": ".000",
              "avg": ".000",
              "bb": "0",
              "fldg": ".000",
              "ops": ".000",
              "hbp": "0",
              "d": "0",
              "e": "0",
              "so": "0",
              "a": "0",
              "s_so": "0",
              "sf": "0",
              "h": "0",
              "cs": "0",
              "obp": ".000",
              "s_bb": "0",
              "s_r": "0",
              "t": "0",
              "ao": "0",
              "r": "0",
              "sb": "0",
              "po": "0",
              "ab": "0"
            },
            {
              "hr": "0",
              "sac": "0",
              "name_display_first_last": "Andrew Miller",
              "s_h": "0",
              "s_hr": "0",
              "s_rbi": "0",
              "pos": "P",
              "id": "453192",
              "rbi": "0",
              "lob": "0",
              "name": "Miller, A",
              "slg": ".000",
              "avg": ".000",
              "bb": "0",
              "fldg": ".000",
              "ops": ".000",
              "hbp": "0",
              "d": "0",
              "e": "0",
              "so": "0",
              "a": "0",
              "s_so": "0",
              "sf": "0",
              "h": "0",
              "cs": "0",
              "obp": ".000",
              "s_bb": "0",
              "s_r": "0",
              "t": "0",
              "ao": "0",
              "r": "0",
              "sb": "0",
              "po": "0",
              "ab": "0"
            },
            {
              "hr": "0",
              "sac": "0",
              "name_display_first_last": "Aroldis Chapman",
              "s_h": "0",
              "s_hr": "0",
              "s_rbi": "0",
              "pos": "P",
              "id": "547973",
              "rbi": "0",
              "lob": "0",
              "name": "Chapman",
              "slg": ".000",
              "avg": ".000",
              "bb": "0",
              "fldg": "1.000",
              "ops": ".000",
              "hbp": "0",
              "d": "0",
              "e": "0",
              "so": "0",
              "a": "0",
              "s_so": "0",
              "sf": "0",
              "h": "0",
              "cs": "0",
              "obp": ".000",
              "s_bb": "0",
              "s_r": "0",
              "t": "0",
              "ao": "0",
              "r": "0",
              "sb": "0",
              "po": "1",
              "ab": "0"
            }
          ],
          "h": "11",
          "text_data_es": "\n         <home_runs>Gregorius (10, 5th entrada ante Bauer, 0 en base, 1 out).<\/home_runs><br/>\n         <total_bases>Ellsbury 2; Headley 2; Castro, S; Gardner 2; Gregorius 5; Refsnyder; McCann, B.<\/total_bases><br/>\n         <rbi>Gregorius (39); Gardner (17); Headley (26); Refsnyder (10); Ellsbury (26).<\/rbi><br/>\n         <two_out_rbi>Gardner; Ellsbury.<\/two_out_rbi><br/>\n         <risp_lob_two_out>McCann, B 2; Hicks; Teixeira.<\/risp_lob_two_out><br/>\n         <sac_flies>Refsnyder.<\/sac_flies><br/>\n         <team_risp>\n            \t\t\t\t\t\t\tde 3-7.\n         <\/team_risp>\n         <team_lob>9.<\/team_lob>\n         <caught_stealing>Ellsbury (7, 2nd base por House/Gimenez).<\/caught_stealing><br/>\n         <picked_off>Ellsbury (1st base por House).<\/picked_off><br/><br/>",
          "text_data": "\n         <home_runs>Gregorius (10, 5th inning off Bauer, 0 on, 1 out).<\/home_runs><br/>\n         <total_bases>Ellsbury 2; Headley 2; Castro, S; Gardner 2; Gregorius 5; Refsnyder; McCann, B.<\/total_bases><br/>\n         <rbi>Gregorius (39); Gardner (17); Headley (26); Refsnyder (10); Ellsbury (26).<\/rbi><br/>\n         <two_out_rbi>Gardner; Ellsbury.<\/two_out_rbi><br/>\n         <risp_lob_two_out>McCann, B 2; Hicks; Teixeira.<\/risp_lob_two_out><br/>\n         <sac_flies>Refsnyder.<\/sac_flies><br/>\n         <team_risp>3-for-7.<\/team_risp>\n         <team_lob>9.<\/team_lob>\n         <caught_stealing>Ellsbury (7, 2nd base by House/Gimenez).<\/caught_stealing><br/>\n         <picked_off>Ellsbury (1st base by House).<\/picked_off><br/><br/>",
          "obp": ".312",
          "rbi": "5",
          "lob": "17",
          "t": "0",
          "r": "5",
          "team_flag": "away",
          "ab": "36",
          "po": "27",
          "slg": ".395",
          "avg": ".251",
          "bb": "4",
          "ops": ".707"
        }
      ],
      "away_sname": "NY Yankees",
      "game_id": "2016/07/07/nyamlb-clemlb-1",
      "home_team_code": "cle",
      "venue_id": "5",
      "home_wins": "51",
      "away_team_code": "nya",
      "away_id": "147",
      "home_fname": "Cleveland Indians"
    }
  }
}
